palladium/R.py
palladium/__init__.py
palladium/cache.py
palladium/config.py
palladium/dataset.py
palladium/eval.py
palladium/fit.py
palladium/interfaces.py
palladium/julia.py
palladium/persistence.py
palladium/server.py
palladium/util.py
palladium/wsgi.py
palladium/tests/__init__.py
palladium/tests/conftest.py
palladium/tests/test_R.py
palladium/tests/test_cache.py
palladium/tests/test_config.py
palladium/tests/test_dataset.py
palladium/tests/test_eval.py
palladium/tests/test_fit.py
palladium/tests/test_interfaces.py
palladium/tests/test_julia.py
palladium/tests/test_persistence.py
palladium/tests/test_server.py
palladium/tests/test_util.py
palladium/tests/test_wsgi.py
palladium-1.2.4.1.data/scripts/pld-dockerize
palladium-1.2.4.1.dist-info/AUTHORS.rst
palladium-1.2.4.1.dist-info/LICENSE
palladium-1.2.4.1.dist-info/METADATA
palladium-1.2.4.1.dist-info/WHEEL
palladium-1.2.4.1.dist-info/entry_points.txt
palladium-1.2.4.1.dist-info/top_level.txt
palladium-1.2.4.1.dist-info/RECORD
