Metadata-Version: 2.1
Name: palladium
Version: 1.2.4.1
Summary: Framework for setting up predictive analytics services
Home-page: https://github.com/ottogroup/palladium
Author: Otto Group
Author-email: palladium@ottogroup.com
License: Apache License, Version 2.0
Platform: UNKNOWN
Classifier: Development Status :: 5 - Production/Stable
Classifier: Intended Audience :: Developers
Classifier: License :: OSI Approved :: Apache Software License
Classifier: Programming Language :: Python :: 3.8
Classifier: Programming Language :: Python :: 3.9
Classifier: Programming Language :: Python :: 3.10
License-File: LICENSE
License-File: AUTHORS.rst
Requires-Dist: docopt
Requires-Dist: flask
Requires-Dist: joblib
Requires-Dist: numpy
Requires-Dist: pandas
Requires-Dist: psutil
Requires-Dist: requests
Requires-Dist: scikit-learn
Requires-Dist: sqlalchemy
Requires-Dist: ujson
Provides-Extra: r
Requires-Dist: rpy2 ; extra == 'r'
Provides-Extra: s3
Requires-Dist: s3fs ; extra == 's3'
Requires-Dist: moto ; extra == 's3'
Provides-Extra: docs
Requires-Dist: Sphinx ; extra == 'docs'
Requires-Dist: sphinx-rtd-theme ; extra == 'docs'
Provides-Extra: julia
Requires-Dist: julia ; extra == 'julia'
Provides-Extra: testing
Requires-Dist: pytest ; extra == 'testing'
Requires-Dist: pytest-cov ; extra == 'testing'
Requires-Dist: requests-mock ; extra == 'testing'
